lightxdb
